README.md
setup.py
CooHSQL/CooHSQL.py
CooHSQL/CooHSQL_Utils.py
CooHSQL/__init__.py
CooHSQL.egg-info/PKG-INFO
CooHSQL.egg-info/SOURCES.txt
CooHSQL.egg-info/dependency_links.txt
CooHSQL.egg-info/requires.txt
CooHSQL.egg-info/top_level.txt