Metadata-Version: 2.1
Name: CooHSQL
Version: 1.0.0
Summary: Apply flashback with DML
Home-page: https://github.com/DooBeDooBa/CooHSQL
Author: HB
Author-email: huabing8023@126.com
Maintainer: HB
License: LICENSE
Platform: UNKNOWN
Requires-Python: >=3.6.0
